{
  "date": "2026-05-19",
  "top_gainers": [
    {
      "symbol": "CORBL",
      "ltp": 2300.0,
      "point_change": 287.0,
      "pct_change": 14.26
    },
    {
      "symbol": "NRM",
      "ltp": 373.5,
      "point_change": 22.5,
      "pct_change": 6.41
    },
    {
      "symbol": "DHEL",
      "ltp": 625.0,
      "point_change": 21.8,
      "pct_change": 3.61
    },
    {
      "symbol": "GIBF1",
      "ltp": 11.01,
      "point_change": 0.33,
      "pct_change": 3.09
    },
    {
      "symbol": "SBID2090",
      "ltp": 1184.5,
      "point_change": 34.5,
      "pct_change": 3.0
    }
  ],
  "top_losers": [
    {
      "symbol": "CITY",
      "ltp": 368.0,
      "point_change": -27.0,
      "pct_change": -6.84
    },
    {
      "symbol": "TSHL",
      "ltp": 550.0,
      "point_change": -34.0,
      "pct_change": -5.82
    },
    {
      "symbol": "PBLD87",
      "ltp": 1043.0,
      "point_change": -59.0,
      "pct_change": -5.35
    },
    {
      "symbol": "JHAPA",
      "ltp": 1509.0,
      "point_change": -69.9,
      "pct_change": -4.43
    },
    {
      "symbol": "KBLD86",
      "ltp": 1122.0,
      "point_change": -40.1,
      "pct_change": -3.45
    }
  ],
  "top_turnover": [
    {
      "symbol": "CITY",
      "turnover": 235335653.3,
      "ltp": 368.0
    },
    {
      "symbol": "SAHAS",
      "turnover": 91635910.7,
      "ltp": 653.0
    },
    {
      "symbol": "AKJCL",
      "turnover": 86833367.0,
      "ltp": 354.0
    },
    {
      "symbol": "CORBL",
      "turnover": 81857365.9,
      "ltp": 2300.0
    },
    {
      "symbol": "SYPNL",
      "turnover": 80759468.2,
      "ltp": 1467.0
    }
  ],
  "top_volume": [
    {
      "symbol": "PRSF",
      "volume": 1050830.0,
      "ltp": 12.98
    },
    {
      "symbol": "CITY",
      "volume": 652647.0,
      "ltp": 368.0
    },
    {
      "symbol": "AKJCL",
      "volume": 248919.0,
      "ltp": 354.0
    },
    {
      "symbol": "HBLPO",
      "volume": 217473.0,
      "ltp": 115.0
    },
    {
      "symbol": "NHPC",
      "volume": 214996.0,
      "ltp": 279.3
    }
  ]
}